.project
.pydevproject
README.txt
setup.py
docs/HISTORY.txt
docs/INSTALL.txt
docs/LICENSE.GPL
docs/LICENSE.txt
redturtle/__init__.py
redturtle.extjs.egg-info/PKG-INFO
redturtle.extjs.egg-info/SOURCES.txt
redturtle.extjs.egg-info/dependency_links.txt
redturtle.extjs.egg-info/entry_points.txt
redturtle.extjs.egg-info/namespace_packages.txt
redturtle.extjs.egg-info/not-zip-safe
redturtle.extjs.egg-info/requires.txt
redturtle.extjs.egg-info/top_level.txt
redturtle/extjs/__init__.py
redturtle/extjs/configure.zcml
redturtle/extjs/extjs/ext-all-debug.js
redturtle/extjs/extjs/ext-all.js
redturtle/extjs/extjs/ext-core-debug.js
redturtle/extjs/extjs/ext-core.js
redturtle/extjs/extjs/ext_adapters/ext/ext-base.js
redturtle/extjs/extjs/ext_adapters/jquery/ext-jquery-adapter.js
redturtle/extjs/extjs/ext_adapters/jquery/jquery.js
redturtle/extjs/extjs/ext_adapters/prototype/effects.js
redturtle/extjs/extjs/ext_adapters/prototype/ext-prototype-adapter.js
redturtle/extjs/extjs/ext_adapters/prototype/prototype.js
redturtle/extjs/extjs/ext_adapters/prototype/scriptaculous.js
redturtle/extjs/extjs/ext_adapters/yui/ext-yui-adapter.js
redturtle/extjs/extjs/ext_adapters/yui/yui-utilities.js
redturtle/extjs/extjs/locale/ext-lang-af.js
redturtle/extjs/extjs/locale/ext-lang-bg.js
redturtle/extjs/extjs/locale/ext-lang-ca.js
redturtle/extjs/extjs/locale/ext-lang-cs.js
redturtle/extjs/extjs/locale/ext-lang-da.js
redturtle/extjs/extjs/locale/ext-lang-de.js
redturtle/extjs/extjs/locale/ext-lang-el_GR.js
redturtle/extjs/extjs/locale/ext-lang-en.js
redturtle/extjs/extjs/locale/ext-lang-en_UK.js
redturtle/extjs/extjs/locale/ext-lang-es.js
redturtle/extjs/extjs/locale/ext-lang-fa.js
redturtle/extjs/extjs/locale/ext-lang-fr.js
redturtle/extjs/extjs/locale/ext-lang-fr_CA.js
redturtle/extjs/extjs/locale/ext-lang-gr.js
redturtle/extjs/extjs/locale/ext-lang-he.js
redturtle/extjs/extjs/locale/ext-lang-hr.js
redturtle/extjs/extjs/locale/ext-lang-hu.js
redturtle/extjs/extjs/locale/ext-lang-id.js
redturtle/extjs/extjs/locale/ext-lang-it.js
redturtle/extjs/extjs/locale/ext-lang-ja.js
redturtle/extjs/extjs/locale/ext-lang-ko.js
redturtle/extjs/extjs/locale/ext-lang-lt.js
redturtle/extjs/extjs/locale/ext-lang-lv.js
redturtle/extjs/extjs/locale/ext-lang-mk.js
redturtle/extjs/extjs/locale/ext-lang-nl.js
