Metadata-Version: 1.0
Name: redturtle.extjs
Version: 0.0.3
Summary: ExtJS in Zope (Plone)
Home-page: http://www.redturtle.net
Author: Andrew Mleczko
Author-email: andrew.mleczko@redturtle.it
License: GPL
Keywords: zope,plone,extjs,javascript
Platform: UNKNOWN
Classifier: Framework :: Plone
Classifier: Programming Language :: Python
Classifier: Topic :: Software Development :: Libraries :: Python Modules
